README.rst
intheam-cli
intheam.py
setup.py
intheam.egg-info/PKG-INFO
intheam.egg-info/SOURCES.txt
intheam.egg-info/dependency_links.txt
intheam.egg-info/requires.txt
intheam.egg-info/top_level.txt