Metadata-Version: 1.1
Name: intheam
Version: 0.0.3
Summary: Wrapper around the inthe.am API
Home-page: https://github.com/aperezdc/intheam-python
Author: Adrián Pérez de Castro
Author-email: adrian@perezdecastro.org
License: MIT
Platform: UNKNOWN
Classifier: Development Status :: 3 - Alpha
Classifier: Intended Audience :: Developers
Classifier: Natural Language :: English
Classifier: Programming Language :: Python :: 3.4
Classifier: Programming Language :: Python
Classifier: Operating System :: OS Independent
